{
   "nodes":{
      "portfolio-node":{
         "CONDITION":{
            "CONDITION":[
               {
                  "OPERATION":"=",
                  "VALUE":"reportDataDictionary:ax_prod_Deposit",
                  "_type":"EXPRESSION_SHORTHAND"
               },
               {
                  "OPERATION":"=",
                  "VALUE":"reportDataDictionary:ax_prod_Loan",
                  "_type":"EXPRESSION_SHORTHAND"
               },
               {
                  "OPERATION":"=",
                  "VALUE":"reportDataDictionary:prod_Repo",
                  "_type":"EXPRESSION_SHORTHAND"
               }
            ],
            "COPULA":[
               "OR",
               "OR"
            ]
         },
         "actions":{
            "param":{
               "_name":"actions"
            },
            "_id":"1b82ab1f-24dd-4594-862f-768bb373f463"
         },
         "models":{
            "model":"Portfolio[UEM_2_b_Rows].Portfolio[UEM_2_b_Columns].Portfolio[UEM_2_a_Columns].ModifyModel[position].reportDataDictionary:position"
         },
         "portfolio-node":[
            {
               "CONDITION":{
                  "CONDITION":{
                     "OPERATION":"=",
                     "VALUE":"reportDataDictionary:prod_Repo",
                     "_type":"EXPRESSION_SHORTHAND"
                  }
               },
               "actions":{
                  "param":{
                     "paramLine":{
                        "param":[
                           {
                              "string":"SET",
                              "_name":"type"
                           },
                           {
                              "string":"PORTFOLIO",
                              "_name":"destinationTable"
                           },
                           {
                              "string":"line_item",
                              "_name":"destinationColumn"
                           },
                           {
                              "string":"$Portfolio_control#line_item[UEM_2_b_Rows].REPO",
                              "_name":"sourceExpression"
                           },
                           {
                              "string":"",
                              "_name":"destinationCondition"
                           }
                        ],
                        "_id":"8b110e47-17a9-49d6-bef6-97919a27542f"
                     },
                     "_name":"actions"
                  },
                  "_id":"56391aef-44ad-468e-976e-7e43d902bcc6"
               },
               "models":{
                  "model":"Portfolio[UEM_2_b_Rows].Portfolio[UEM_2_b_Columns].Portfolio[UEM_2_a_Columns].ModifyModel[position].reportDataDictionary:position"
               },
               "_comment":"",
               "_description":"Repurchase agreements",
               "_docFile":"",
               "_expandedConditionsIncludeInherited":"false",
               "_expandedConditionsModel":"",
               "_id":"5ce86882-0004-4c50-9bf3-0f09db19843d",
               "_name":"REPO"
            },
            {
               "CONDITION":"",
               "actions":{
                  "param":{
                     "_name":"actions"
                  },
                  "_id":"a1506e91-f308-40bc-aff5-862bb6d25d96"
               },
               "models":{
                  "model":"Portfolio[UEM_2_b_Rows].Portfolio[UEM_2_b_Columns].Portfolio[UEM_2_a_Columns].ModifyModel[position].reportDataDictionary:position"
               },
               "portfolio-node":[
                  {
                     "CONDITION":{
                        "CONDITION":[
                           {
                              "OPERATION":"=",
                              "VALUE":"reportDataDictionary:isLoanDeposit_Overnight",
                              "_type":"EXPRESSION_SHORTHAND"
                           },
                           {
                              "OPERATION":"=",
                              "VALUE":"reportDataDictionary:isLoanDeposit_Sight",
                              "_type":"EXPRESSION_SHORTHAND"
                           },
                           {
                              "CONDITION":[
                                 {
                                    "OPERATION":"=",
                                    "VALUE":"reportDataDictionary:isLoanDepositTerm_Unallocated",
                                    "_type":"EXPRESSION_SHORTHAND"
                                 },
                                 {
                                    "OPERATION":"=",
                                    "VALUE":"reportDataDictionary:ntcePeriod_IsUnallocated",
                                    "_type":"EXPRESSION_SHORTHAND"
                                 }
                              ],
                              "COPULA":"AND"
                           }
                        ],
                        "COPULA":[
                           "OR",
                           "OR"
                        ]
                     },
                     "actions":{
                        "param":{
                           "paramLine":{
                              "param":[
                                 {
                                    "string":"SET",
                                    "_name":"type"
                                 },
                                 {
                                    "string":"PORTFOLIO",
                                    "_name":"destinationTable"
                                 },
                                 {
                                    "string":"line_item",
                                    "_name":"destinationColumn"
                                 },
                                 {
                                    "string":"$Portfolio_control#line_item[UEM_2_b_Rows].ON1",
                                    "_name":"sourceExpression"
                                 },
                                 {
                                    "string":"",
                                    "_name":"destinationCondition"
                                 }
                              ],
                              "_id":"9ca250b7-f171-467d-a4ad-30abdd3bd00e"
                           },
                           "_name":"actions"
                        },
                        "_id":"3f454375-3d0e-4080-94a1-1cf11cf76b35"
                     },
                     "models":{
                        "model":"Portfolio[UEM_2_b_Rows].Portfolio[UEM_2_b_Columns].Portfolio[UEM_2_a_Columns].ModifyModel[position].reportDataDictionary:position"
                     },
                     "_comment":"",
                     "_description":"At A Glance",
                     "_docFile":"",
                     "_expandedConditionsIncludeInherited":"false",
                     "_expandedConditionsModel":"",
                     "_id":"69e8511b-30c4-4d79-893b-32d6658861cd",
                     "_name":"ON"
                  },
                  {
                     "CONDITION":{
                        "CONDITION":[
                           {
                              "OPERATION":"=",
                              "VALUE":"reportDataDictionary:origMat_LE2Years",
                              "_type":"EXPRESSION_SHORTHAND"
                           },
                           {
                              "OPERATION":"=",
                              "VALUE":"reportDataDictionary:isLoanDeposit_Term",
                              "_type":"EXPRESSION_SHORTHAND"
                           },
                           {
                              "OPERATION":"=",
                              "VALUE":"reportDataDictionary:ntcePeriod_IsUnallocated",
                              "_type":"EXPRESSION_SHORTHAND"
                           }
                        ],
                        "COPULA":[
                           "AND",
                           "AND"
                        ]
                     },
                     "actions":{
                        "param":{
                           "_name":"actions"
                        },
                        "_id":"fd254f42-dc78-464d-aa96-35c31ce4309c"
                     },
                     "models":{
                        "model":"Portfolio[UEM_2_b_Rows].Portfolio[UEM_2_b_Columns].Portfolio[UEM_2_a_Columns].ModifyModel[position].reportDataDictionary:position"
                     },
                     "portfolio-node":[
                        {
                           "CONDITION":{
                              "CONDITION":{
                                 "OPERATION":"=",
                                 "VALUE":"reportDataDictionary:origMat_LE1Year",
                                 "_type":"EXPRESSION_SHORTHAND"
                              }
                           },
                           "actions":{
                              "param":{
                                 "paramLine":{
                                    "param":[
                                       {
                                          "string":"SET",
                                          "_name":"type"
                                       },
                                       {
                                          "string":"PORTFOLIO",
                                          "_name":"destinationTable"
                                       },
                                       {
                                          "string":"line_item",
                                          "_name":"destinationColumn"
                                       },
                                       {
                                          "string":"@isNull($Portfolio_control#line_item[UEM_2_b_Rows].LE2_LE1Y, $Portfolio_control#line_item[UEM_2_b_Rows].LE2)",
                                          "_name":"sourceExpression"
                                       },
                                       {
                                          "string":"",
                                          "_name":"destinationCondition"
                                       }
                                    ],
                                    "_id":"2a19056c-9280-4072-b9d2-fd28d958640d"
                                 },
                                 "_name":"actions"
                              },
                              "_id":"0ee4c9bf-b65f-42f1-9064-c3c7a7a6549e"
                           },
                           "models":{
                              "model":"Portfolio[UEM_2_b_Rows].Portfolio[UEM_2_b_Columns].Portfolio[UEM_2_a_Columns].ModifyModel[position].reportDataDictionary:position"
                           },
                           "_comment":"",
                           "_description":"Up to 1 year",
                           "_docFile":"",
                           "_expandedConditionsIncludeInherited":"false",
                           "_expandedConditionsModel":"",
                           "_id":"72cd4a02-73a3-4134-a22f-2d68473997a4",
                           "_name":"LE2_LE1Y"
                        },
                        {
                           "CONDITION":"",
                           "actions":{
                              "param":{
                                 "paramLine":{
                                    "param":[
                                       {
                                          "string":"SET",
                                          "_name":"type"
                                       },
                                       {
                                          "string":"PORTFOLIO",
                                          "_name":"destinationTable"
                                       },
                                       {
                                          "string":"line_item",
                                          "_name":"destinationColumn"
                                       },
                                       {
                                          "string":"@isNull($Portfolio_control#line_item[UEM_2_b_Rows].LE2_G1Y, $Portfolio_control#line_item[UEM_2_b_Rows].LE2)",
                                          "_name":"sourceExpression"
                                       },
                                       {
                                          "string":"",
                                          "_name":"destinationCondition"
                                       }
                                    ],
                                    "_id":"85603e8f-cfe0-4682-a533-34b564d194ea"
                                 },
                                 "_name":"actions"
                              },
                              "_id":"06f397ef-d1e9-4568-a79e-a5f6a19caf89"
                           },
                           "models":{
                              "model":"Portfolio[UEM_2_b_Rows].Portfolio[UEM_2_b_Columns].Portfolio[UEM_2_a_Columns].ModifyModel[position].reportDataDictionary:position"
                           },
                           "_comment":"",
                           "_description":"More than 1 year and up to 2 years",
                           "_docFile":"",
                           "_expandedConditionsIncludeInherited":"false",
                           "_expandedConditionsModel":"",
                           "_id":"009a1fc1-15a8-4254-980e-1837bfec07bc",
                           "_name":"LE2_G1Y"
                        }
                     ],
                     "_comment":"",
                     "_description":"Up to 2 Years",
                     "_docFile":"",
                     "_expandedConditionsIncludeInherited":"false",
                     "_expandedConditionsModel":"",
                     "_id":"4222e9b7-d001-428e-8a76-8972aea33a1d",
                     "_name":"LE2Y"
                  },
                  {
                     "CONDITION":{
                        "CONDITION":[
                           {
                              "OPERATION":"=",
                              "VALUE":"reportDataDictionary:origMat_LE2Years",
                              "_type":"EXPRESSION_SHORTHAND"
                           },
                           {
                              "OPERATION":"=",
                              "VALUE":"reportDataDictionary:isLoanDeposit_Term",
                              "_type":"EXPRESSION_SHORTHAND"
                           },
                           {
                              "OPERATION":"=",
                              "VALUE":"reportDataDictionary:ntcePeriod_IsUnallocated",
                              "_type":"EXPRESSION_SHORTHAND"
                           }
                        ],
                        "COPULA":[
                           "AND",
                           "AND"
                        ]
                     },
                     "actions":{
                        "param":{
                           "paramLine":{
                              "param":[
                                 {
                                    "string":"SET",
                                    "_name":"type"
                                 },
                                 {
                                    "string":"PORTFOLIO",
                                    "_name":"destinationTable"
                                 },
                                 {
                                    "string":"line_item",
                                    "_name":"destinationColumn"
                                 },
                                 {
                                    "string":"$Portfolio_control#line_item[UEM_2_b_Rows].G2",
                                    "_name":"sourceExpression"
                                 },
                                 {
                                    "string":"",
                                    "_name":"destinationCondition"
                                 }
                              ],
                              "_id":"7e0ae9ff-a04d-4310-a34d-0a065c5aa5af"
                           },
                           "_name":"actions"
                        },
                        "_id":"1d47ecf2-c124-4d1a-845c-b8f6b78a0f2d"
                     },
                     "models":{
                        "model":"Portfolio[UEM_2_b_Rows].Portfolio[UEM_2_b_Columns].Portfolio[UEM_2_a_Columns].ModifyModel[position].reportDataDictionary:position"
                     },
                     "_comment":"",
                     "_description":"A term of more than 2 years",
                     "_docFile":"",
                     "_expandedConditionsIncludeInherited":"false",
                     "_expandedConditionsModel":"",
                     "_id":"82d9a11c-254b-45f4-a7a4-728cf221c843",
                     "_name":"G2Y"
                  },
                  {
                     "CONDITION":{
                        "CONDITION":{
                           "OPERATION":"!=",
                           "VALUE":"reportDataDictionary:ntcePeriod_IsUnallocated",
                           "_type":"EXPRESSION_SHORTHAND"
                        }
                     },
                     "actions":{
                        "param":{
                           "_name":"actions"
                        },
                        "_id":"1b7ab920-52ab-43e3-82df-7adf7db1a395"
                     },
                     "models":{
                        "model":"Portfolio[UEM_2_b_Rows].Portfolio[UEM_2_b_Columns].Portfolio[UEM_2_a_Columns].ModifyModel[position].reportDataDictionary:position"
                     },
                     "portfolio-node":[
                        {
                           "CONDITION":{
                              "CONDITION":{
                                 "OPERATION":"=",
                                 "VALUE":"reportDataDictionary:ntcePeriod_LE3Months",
                                 "_type":"EXPRESSION_SHORTHAND"
                              }
                           },
                           "actions":{
                              "param":{
                                 "paramLine":{
                                    "param":[
                                       {
                                          "string":"SET",
                                          "_name":"type"
                                       },
                                       {
                                          "string":"PORTFOLIO",
                                          "_name":"destinationTable"
                                       },
                                       {
                                          "string":"line_item",
                                          "_name":"destinationColumn"
                                       },
                                       {
                                          "string":"@isNull($Portfolio_control#line_item[UEM_2_b_Rows].SN_LE3M, $Portfolio_control#line_item[UEM_2_b_Rows].SN)",
                                          "_name":"sourceExpression"
                                       },
                                       {
                                          "string":"",
                                          "_name":"destinationCondition"
                                       }
                                    ],
                                    "_id":"97d84892-7be9-4be0-88df-0a26850dd7c1"
                                 },
                                 "_name":"actions"
                              },
                              "_id":"dfbb0c65-466f-4224-b84f-2eccf4160c30"
                           },
                           "models":{
                              "model":"Portfolio[UEM_2_b_Rows].Portfolio[UEM_2_b_Columns].Portfolio[UEM_2_a_Columns].ModifyModel[position].reportDataDictionary:position"
                           },
                           "_comment":"",
                           "_description":"Up to 3 months",
                           "_docFile":"",
                           "_expandedConditionsIncludeInherited":"false",
                           "_expandedConditionsModel":"",
                           "_id":"930a8277-6878-42c8-8684-b13969475b7f",
                           "_name":"SN_LE3M"
                        },
                        {
                           "CONDITION":"",
                           "actions":{
                              "param":{
                                 "paramLine":{
                                    "param":[
                                       {
                                          "string":"SET",
                                          "_name":"type"
                                       },
                                       {
                                          "string":"PORTFOLIO",
                                          "_name":"destinationTable"
                                       },
                                       {
                                          "string":"line_item",
                                          "_name":"destinationColumn"
                                       },
                                       {
                                          "string":"@isNull($Portfolio_control#line_item[UEM_2_b_Rows].SN_G3M, $Portfolio_control#line_item[UEM_2_b_Rows].SN)",
                                          "_name":"sourceExpression"
                                       },
                                       {
                                          "string":"",
                                          "_name":"destinationCondition"
                                       }
                                    ],
                                    "_id":"2249b95c-b6d9-4f2b-a14a-3754f89fbbc8"
                                 },
                                 "_name":"actions"
                              },
                              "_id":"ab5ec6ec-7848-4079-bb7e-fc869867000b"
                           },
                           "models":{
                              "model":"Portfolio[UEM_2_b_Rows].Portfolio[UEM_2_b_Columns].Portfolio[UEM_2_a_Columns].ModifyModel[position].reportDataDictionary:position"
                           },
                           "_comment":"",
                           "_description":"More than 3 months",
                           "_docFile":"",
                           "_expandedConditionsIncludeInherited":"false",
                           "_expandedConditionsModel":"",
                           "_id":"05dfbd88-f38d-4f08-aee0-d481f83db618",
                           "_name":"SN_G3M"
                        }
                     ],
                     "_comment":"",
                     "_description":"Available at short notice",
                     "_docFile":"",
                     "_expandedConditionsIncludeInherited":"false",
                     "_expandedConditionsModel":"",
                     "_id":"2a101e3d-f934-49dc-8b7e-dfeaf48ecb36",
                     "_name":"SN"
                  }
               ],
               "_comment":"",
               "_description":"Loans and Deposits",
               "_docFile":"",
               "_expandedConditionsIncludeInherited":"false",
               "_expandedConditionsModel":"",
               "_id":"d6394979-ea2e-4fe5-86cb-60b3098c7667",
               "_name":"LOANS_AND_DEPOSITS"
            },
            {
               "CONDITION":"",
               "actions":{
                  "param":{
                     "_name":"actions"
                  },
                  "_id":"08619af4-43b5-4d9a-823c-28af1f239ae4"
               },
               "models":{
                  "model":"Portfolio[UEM_2_b_Rows].Portfolio[UEM_2_b_Columns].Portfolio[UEM_2_a_Columns].ModifyModel[position].reportDataDictionary:position"
               },
               "_comment":"",
               "_description":"Orphans",
               "_docFile":"",
               "_expandedConditionsIncludeInherited":"false",
               "_expandedConditionsModel":"",
               "_id":"1bb5b27e-a135-4270-b5e5-51752622cec8",
               "_name":"Orphans"
            }
         ],
         "_comment":"",
         "_description":"SUMMARY BALANCE (BUSINESS IN SPAIN) (b) [2260]",
         "_docFile":"",
         "_expandedConditionsIncludeInherited":"false",
         "_expandedConditionsModel":"",
         "_id":"",
         "_name":"UEM_2_b_Maturity"
      }
   }
}