{
   "nodes":{
      "parameterNode":{
         "parameterNode":[
            {
               "parameterNode":[
                  {
                     "parameters":{
                        "param":{
                           "paramLine":{
                              "param":[
                                 {
                                    "string":"Motor_saldos:ModifyModel[carga_saldos].Aggregation[BBEE_PRE]",
                                    "_name":"model"
                                 },
                                 {
                                    "string":"$Aggregation.mvyt24be_company",
                                    "_name":"expression"
                                 },
                                 {
                                    "string":"VARCHAR",
                                    "_name":"valueType"
                                 }
                              ],
                              "_id":"3aaa3bdd-6dc6-4309-a1da-d1bb9b0f2ada:ModifyModel[1efebe4a-1dcb-4dcb-9623-079468ae41d2].Aggregation[8d725237-1404-45ca-b175-4e3043d19068]"
                           },
                           "_name":"fieldMapping"
                        },
                        "_id":"d528d859-d3fb-4597-8e95-b0be21d4f4b4"
                     },
                     "_name":"company",
                     "_type":"fieldMappingNode"
                  },
                  {
                     "parameters":{
                        "param":{
                           "paramLine":{
                              "param":[
                                 {
                                    "string":"Motor_saldos:ModifyModel[carga_saldos].Aggregation[BBEE_PRE]",
                                    "_name":"model"
                                 },
                                 {
                                    "string":"$Aggregation.mvyt24be_contract_id",
                                    "_name":"expression"
                                 },
                                 {
                                    "string":"VARCHAR",
                                    "_name":"valueType"
                                 }
                              ],
                              "_id":"3aaa3bdd-6dc6-4309-a1da-d1bb9b0f2ada:ModifyModel[1efebe4a-1dcb-4dcb-9623-079468ae41d2].Aggregation[8d725237-1404-45ca-b175-4e3043d19068]"
                           },
                           "_name":"fieldMapping"
                        },
                        "_id":"ed6bb169-36ad-4f0e-a2aa-d10b5f709b66"
                     },
                     "_name":"contract_id",
                     "_type":"fieldMappingNode"
                  }
               ],
               "_name":"Details Mapping",
               "_type":"detailGroup"
            },
            {
               "parameterNode":[
                  {
                     "parameters":{
                        "param":{
                           "paramLine":{
                              "param":[
                                 {
                                    "string":"Motor_saldos:ModifyModel[carga_saldos].Aggregation[BBEE_PRE]",
                                    "_name":"model"
                                 },
                                 {
                                    "string":"CASE WHEN @subStr(@dateToCharODBCFormat(@ASOF_DATE), 6, 2) = '01' THEN (CASE WHEN @ASOF_DATE = $Aggregation.mvyt24be_start_date THEN $Aggregation.mvyt24be_lcy_amount ELSE (CASE WHEN subStr(@dateToCharODBCFormat(@ASOF_DATE), 9,2) = '01' THEN $Aggregation.mvyt24be_lcy_amount ELSE (CASE WHEN @subStr(@dateToCharODBCFormat(@ASOF_DATE), 1, 7) = @subStr(@dateToCharODBCFormat($Aggregation.mvyt24be_start_date), 1, 7) THEN (CASE WHEN $saldos_medios_prev.saldo_medio_01 IS NULL THEN $Aggregation.mvyt24be_lcy_amount/(@dateDiff($Aggregation.mvyt24be_start_date, @ASOF_DATE)+1) ELSE (($saldos_medios_prev.saldo_medio_01*(@dateDiff($Aggregation.mvyt24be_start_date, @ASOF_DATE)))+$Aggregation.mvyt24be_lcy_amount)/(@dateDiff($Aggregation.mvyt24be_start_date, @ASOF_DATE)+1) END) ELSE (CASE WHEN $saldos_medios_prev.saldo_medio_01 IS NULL THEN $Aggregation.mvyt24be_lcy_amount/(@toNumber(@subStr(@dateToCharODBCFormat(@ASOF_DATE), 9, 2))) ELSE (($saldos_medios_prev.saldo_medio_01*(@toNumber(@subStr(@dateToCharODBCFormat(@ASOF_DATE), 9, 2))-1))+$Aggregation.mvyt24be_lcy_amount)/(@toNumber(@subStr(@dateToCharODBCFormat(@ASOF_DATE), 9, 2))) END) END) END) END) ELSE (CASE WHEN $saldos_medios_prev.saldo_medio_01 IS NULL THEN 0 ELSE $saldos_medios_prev.saldo_medio_01 END) END",
                                    "_name":"expression"
                                 },
                                 {
                                    "string":"FLOAT",
                                    "_name":"valueType"
                                 },
                                 {
                                    "false":"",
                                    "_name":"valueNullable"
                                 }
                              ],
                              "_id":"3aaa3bdd-6dc6-4309-a1da-d1bb9b0f2ada:ModifyModel[1efebe4a-1dcb-4dcb-9623-079468ae41d2].Aggregation[8d725237-1404-45ca-b175-4e3043d19068]"
                           },
                           "_name":"fieldMapping"
                        },
                        "_id":"353eb428-9ded-4459-b79a-ac02e1c0f5fb"
                     },
                     "_name":"saldo_medio_01",
                     "_type":"fieldMappingNode"
                  },
                  {
                     "parameters":{
                        "param":{
                           "paramLine":{
                              "param":[
                                 {
                                    "string":"Motor_saldos:ModifyModel[carga_saldos].Aggregation[BBEE_PRE]",
                                    "_name":"model"
                                 },
                                 {
                                    "string":"CASE WHEN @subStr(@dateToCharODBCFormat(@ASOF_DATE), 6, 2) = '02' THEN (CASE WHEN @ASOF_DATE = $Aggregation.mvyt24be_start_date THEN $Aggregation.mvyt24be_lcy_amount ELSE (CASE WHEN subStr(@dateToCharODBCFormat(@ASOF_DATE), 9,2) = '02' THEN $Aggregation.mvyt24be_lcy_amount ELSE (CASE WHEN @subStr(@dateToCharODBCFormat(@ASOF_DATE), 1, 7) = @subStr(@dateToCharODBCFormat($Aggregation.mvyt24be_start_date), 1, 7) THEN (CASE WHEN $saldos_medios_prev.saldo_medio_02 IS NULL THEN $Aggregation.mvyt24be_lcy_amount/(@dateDiff($Aggregation.mvyt24be_start_date, @ASOF_DATE)+1) ELSE (($saldos_medios_prev.saldo_medio_02*(@dateDiff($Aggregation.mvyt24be_start_date, @ASOF_DATE)))+$Aggregation.mvyt24be_lcy_amount)/(@dateDiff($Aggregation.mvyt24be_start_date, @ASOF_DATE)+1) END) ELSE (CASE WHEN $saldos_medios_prev.saldo_medio_02 IS NULL THEN $Aggregation.mvyt24be_lcy_amount/(@toNumber(@subStr(@dateToCharODBCFormat(@ASOF_DATE), 9, 2))) ELSE (($saldos_medios_prev.saldo_medio_02*(@toNumber(@subStr(@dateToCharODBCFormat(@ASOF_DATE), 9, 2))-1))+$Aggregation.mvyt24be_lcy_amount)/(@toNumber(@subStr(@dateToCharODBCFormat(@ASOF_DATE), 9, 2))) END) END) END) END) ELSE (CASE WHEN $saldos_medios_prev.saldo_medio_02 IS NULL THEN 0 ELSE $saldos_medios_prev.saldo_medio_02 END) END",
                                    "_name":"expression"
                                 },
                                 {
                                    "string":"FLOAT",
                                    "_name":"valueType"
                                 },
                                 {
                                    "false":"",
                                    "_name":"valueNullable"
                                 }
                              ],
                              "_id":"3aaa3bdd-6dc6-4309-a1da-d1bb9b0f2ada:ModifyModel[1efebe4a-1dcb-4dcb-9623-079468ae41d2].Aggregation[8d725237-1404-45ca-b175-4e3043d19068]"
                           },
                           "_name":"fieldMapping"
                        },
                        "_id":"b99dbf9d-9b59-4ee3-ac8f-13f212e0c08a"
                     },
                     "_name":"saldo_medio_02",
                     "_type":"fieldMappingNode"
                  },
                  {
                     "parameters":{
                        "param":{
                           "paramLine":{
                              "param":[
                                 {
                                    "string":"Motor_saldos:ModifyModel[carga_saldos].Aggregation[BBEE_PRE]",
                                    "_name":"model"
                                 },
                                 {
                                    "string":"CASE WHEN @subStr(@dateToCharODBCFormat(@ASOF_DATE), 6, 2) = '03' THEN (CASE WHEN @ASOF_DATE = $Aggregation.mvyt24be_start_date THEN $Aggregation.mvyt24be_lcy_amount ELSE (CASE WHEN subStr(@dateToCharODBCFormat(@ASOF_DATE), 9,2) = '03' THEN $Aggregation.mvyt24be_lcy_amount ELSE (CASE WHEN @subStr(@dateToCharODBCFormat(@ASOF_DATE), 1, 7) = @subStr(@dateToCharODBCFormat($Aggregation.mvyt24be_start_date), 1, 7) THEN (CASE WHEN $saldos_medios_prev.saldo_medio_03 IS NULL THEN $Aggregation.mvyt24be_lcy_amount/(@dateDiff($Aggregation.mvyt24be_start_date, @ASOF_DATE)+1) ELSE (($saldos_medios_prev.saldo_medio_03*(@dateDiff($Aggregation.mvyt24be_start_date, @ASOF_DATE)))+$Aggregation.mvyt24be_lcy_amount)/(@dateDiff($Aggregation.mvyt24be_start_date, @ASOF_DATE)+1) END) ELSE (CASE WHEN $saldos_medios_prev.saldo_medio_03 IS NULL THEN $Aggregation.mvyt24be_lcy_amount/(@toNumber(@subStr(@dateToCharODBCFormat(@ASOF_DATE), 9, 2))) ELSE (($saldos_medios_prev.saldo_medio_03*(@toNumber(@subStr(@dateToCharODBCFormat(@ASOF_DATE), 9, 2))-1))+$Aggregation.mvyt24be_lcy_amount)/(@toNumber(@subStr(@dateToCharODBCFormat(@ASOF_DATE), 9, 2))) END) END) END) END) ELSE (CASE WHEN $saldos_medios_prev.saldo_medio_03 IS NULL THEN 0 ELSE $saldos_medios_prev.saldo_medio_03 END) END",
                                    "_name":"expression"
                                 },
                                 {
                                    "string":"FLOAT",
                                    "_name":"valueType"
                                 },
                                 {
                                    "false":"",
                                    "_name":"valueNullable"
                                 }
                              ],
                              "_id":"3aaa3bdd-6dc6-4309-a1da-d1bb9b0f2ada:ModifyModel[1efebe4a-1dcb-4dcb-9623-079468ae41d2].Aggregation[8d725237-1404-45ca-b175-4e3043d19068]"
                           },
                           "_name":"fieldMapping"
                        },
                        "_id":"eb3864b0-9055-4737-a817-7ef7bb9f0a6c"
                     },
                     "_name":"saldo_medio_03",
                     "_type":"fieldMappingNode"
                  },
                  {
                     "parameters":{
                        "param":{
                           "paramLine":{
                              "param":[
                                 {
                                    "string":"Motor_saldos:ModifyModel[carga_saldos].Aggregation[BBEE_PRE]",
                                    "_name":"model"
                                 },
                                 {
                                    "string":"CASE WHEN @subStr(@dateToCharODBCFormat(@ASOF_DATE), 6, 2) = '04' THEN (CASE WHEN @ASOF_DATE = $Aggregation.mvyt24be_start_date THEN $Aggregation.mvyt24be_lcy_amount ELSE (CASE WHEN subStr(@dateToCharODBCFormat(@ASOF_DATE), 9,2) = '04' THEN $Aggregation.mvyt24be_lcy_amount ELSE (CASE WHEN @subStr(@dateToCharODBCFormat(@ASOF_DATE), 1, 7) = @subStr(@dateToCharODBCFormat($Aggregation.mvyt24be_start_date), 1, 7) THEN (CASE WHEN $saldos_medios_prev.saldo_medio_04 IS NULL THEN $Aggregation.mvyt24be_lcy_amount/(@dateDiff($Aggregation.mvyt24be_start_date, @ASOF_DATE)+1) ELSE (($saldos_medios_prev.saldo_medio_04*(@dateDiff($Aggregation.mvyt24be_start_date, @ASOF_DATE)))+$Aggregation.mvyt24be_lcy_amount)/(@dateDiff($Aggregation.mvyt24be_start_date, @ASOF_DATE)+1) END) ELSE (CASE WHEN $saldos_medios_prev.saldo_medio_04 IS NULL THEN $Aggregation.mvyt24be_lcy_amount/(@toNumber(@subStr(@dateToCharODBCFormat(@ASOF_DATE), 9, 2))) ELSE (($saldos_medios_prev.saldo_medio_04*(@toNumber(@subStr(@dateToCharODBCFormat(@ASOF_DATE), 9, 2))-1))+$Aggregation.mvyt24be_lcy_amount)/(@toNumber(@subStr(@dateToCharODBCFormat(@ASOF_DATE), 9, 2))) END) END) END) END) ELSE (CASE WHEN $saldos_medios_prev.saldo_medio_04 IS NULL THEN 0 ELSE $saldos_medios_prev.saldo_medio_04 END) END",
                                    "_name":"expression"
                                 },
                                 {
                                    "string":"FLOAT",
                                    "_name":"valueType"
                                 },
                                 {
                                    "false":"",
                                    "_name":"valueNullable"
                                 }
                              ],
                              "_id":"3aaa3bdd-6dc6-4309-a1da-d1bb9b0f2ada:ModifyModel[1efebe4a-1dcb-4dcb-9623-079468ae41d2].Aggregation[8d725237-1404-45ca-b175-4e3043d19068]"
                           },
                           "_name":"fieldMapping"
                        },
                        "_id":"1e275594-6287-4856-9462-345a78d5655a"
                     },
                     "_name":"saldo_medio_04",
                     "_type":"fieldMappingNode"
                  },
                  {
                     "parameters":{
                        "param":{
                           "paramLine":{
                              "param":[
                                 {
                                    "string":"Motor_saldos:ModifyModel[carga_saldos].Aggregation[BBEE_PRE]",
                                    "_name":"model"
                                 },
                                 {
                                    "string":"CASE WHEN @subStr(@dateToCharODBCFormat(@ASOF_DATE), 6, 2) = '05' THEN (CASE WHEN @ASOF_DATE = $Aggregation.mvyt24be_start_date THEN $Aggregation.mvyt24be_lcy_amount ELSE (CASE WHEN subStr(@dateToCharODBCFormat(@ASOF_DATE), 9,2) = '05' THEN $Aggregation.mvyt24be_lcy_amount ELSE (CASE WHEN @subStr(@dateToCharODBCFormat(@ASOF_DATE), 1, 7) = @subStr(@dateToCharODBCFormat($Aggregation.mvyt24be_start_date), 1, 7) THEN (CASE WHEN $saldos_medios_prev.saldo_medio_05 IS NULL THEN $Aggregation.mvyt24be_lcy_amount/(@dateDiff($Aggregation.mvyt24be_start_date, @ASOF_DATE)+1) ELSE (($saldos_medios_prev.saldo_medio_05*(@dateDiff($Aggregation.mvyt24be_start_date, @ASOF_DATE)))+$Aggregation.mvyt24be_lcy_amount)/(@dateDiff($Aggregation.mvyt24be_start_date, @ASOF_DATE)+1) END) ELSE (CASE WHEN $saldos_medios_prev.saldo_medio_05 IS NULL THEN $Aggregation.mvyt24be_lcy_amount/(@toNumber(@subStr(@dateToCharODBCFormat(@ASOF_DATE), 9, 2))) ELSE (($saldos_medios_prev.saldo_medio_05*(@toNumber(@subStr(@dateToCharODBCFormat(@ASOF_DATE), 9, 2))-1))+$Aggregation.mvyt24be_lcy_amount)/(@toNumber(@subStr(@dateToCharODBCFormat(@ASOF_DATE), 9, 2))) END) END) END) END) ELSE (CASE WHEN $saldos_medios_prev.saldo_medio_05 IS NULL THEN 0 ELSE $saldos_medios_prev.saldo_medio_05 END) END",
                                    "_name":"expression"
                                 },
                                 {
                                    "string":"FLOAT",
                                    "_name":"valueType"
                                 },
                                 {
                                    "false":"",
                                    "_name":"valueNullable"
                                 }
                              ],
                              "_id":"3aaa3bdd-6dc6-4309-a1da-d1bb9b0f2ada:ModifyModel[1efebe4a-1dcb-4dcb-9623-079468ae41d2].Aggregation[8d725237-1404-45ca-b175-4e3043d19068]"
                           },
                           "_name":"fieldMapping"
                        },
                        "_id":"4e86c16b-b8b6-4f10-b771-f773ceceae06"
                     },
                     "_name":"saldo_medio_05",
                     "_type":"fieldMappingNode"
                  },
                  {
                     "parameters":{
                        "param":{
                           "paramLine":{
                              "param":[
                                 {
                                    "string":"Motor_saldos:ModifyModel[carga_saldos].Aggregation[BBEE_PRE]",
                                    "_name":"model"
                                 },
                                 {
                                    "string":"CASE WHEN @subStr(@dateToCharODBCFormat(@ASOF_DATE), 6, 2) = '06' THEN (CASE WHEN @ASOF_DATE = $Aggregation.mvyt24be_start_date THEN $Aggregation.mvyt24be_lcy_amount ELSE (CASE WHEN subStr(@dateToCharODBCFormat(@ASOF_DATE), 9,2) = '06' THEN $Aggregation.mvyt24be_lcy_amount ELSE (CASE WHEN @subStr(@dateToCharODBCFormat(@ASOF_DATE), 1, 7) = @subStr(@dateToCharODBCFormat($Aggregation.mvyt24be_start_date), 1, 7) THEN (CASE WHEN $saldos_medios_prev.saldo_medio_06 IS NULL THEN $Aggregation.mvyt24be_lcy_amount/(@dateDiff($Aggregation.mvyt24be_start_date, @ASOF_DATE)+1) ELSE (($saldos_medios_prev.saldo_medio_06*(@dateDiff($Aggregation.mvyt24be_start_date, @ASOF_DATE)))+$Aggregation.mvyt24be_lcy_amount)/(@dateDiff($Aggregation.mvyt24be_start_date, @ASOF_DATE)+1) END) ELSE (CASE WHEN $saldos_medios_prev.saldo_medio_06 IS NULL THEN $Aggregation.mvyt24be_lcy_amount/(@toNumber(@subStr(@dateToCharODBCFormat(@ASOF_DATE), 9, 2))) ELSE (($saldos_medios_prev.saldo_medio_06*(@toNumber(@subStr(@dateToCharODBCFormat(@ASOF_DATE), 9, 2))-1))+$Aggregation.mvyt24be_lcy_amount)/(@toNumber(@subStr(@dateToCharODBCFormat(@ASOF_DATE), 9, 2))) END) END) END) END) ELSE (CASE WHEN $saldos_medios_prev.saldo_medio_06 IS NULL THEN 0 ELSE $saldos_medios_prev.saldo_medio_06 END) END",
                                    "_name":"expression"
                                 },
                                 {
                                    "string":"FLOAT",
                                    "_name":"valueType"
                                 },
                                 {
                                    "false":"",
                                    "_name":"valueNullable"
                                 }
                              ],
                              "_id":"3aaa3bdd-6dc6-4309-a1da-d1bb9b0f2ada:ModifyModel[1efebe4a-1dcb-4dcb-9623-079468ae41d2].Aggregation[8d725237-1404-45ca-b175-4e3043d19068]"
                           },
                           "_name":"fieldMapping"
                        },
                        "_id":"ab8abf66-2760-4ed0-86c2-4b6ab75c0cca"
                     },
                     "_name":"saldo_medio_06",
                     "_type":"fieldMappingNode"
                  },
                  {
                     "parameters":{
                        "param":{
                           "paramLine":{
                              "param":[
                                 {
                                    "string":"Motor_saldos:ModifyModel[carga_saldos].Aggregation[BBEE_PRE]",
                                    "_name":"model"
                                 },
                                 {
                                    "string":"CASE WHEN @subStr(@dateToCharODBCFormat(@ASOF_DATE), 6, 2) = '07' THEN (CASE WHEN @ASOF_DATE = $Aggregation.mvyt24be_start_date THEN $Aggregation.mvyt24be_lcy_amount ELSE (CASE WHEN subStr(@dateToCharODBCFormat(@ASOF_DATE), 9,2) = '07' THEN $Aggregation.mvyt24be_lcy_amount ELSE (CASE WHEN @subStr(@dateToCharODBCFormat(@ASOF_DATE), 1, 7) = @subStr(@dateToCharODBCFormat($Aggregation.mvyt24be_start_date), 1, 7) THEN (CASE WHEN $saldos_medios_prev.saldo_medio_07 IS NULL THEN $Aggregation.mvyt24be_lcy_amount/(@dateDiff($Aggregation.mvyt24be_start_date, @ASOF_DATE)+1) ELSE (($saldos_medios_prev.saldo_medio_07*(@dateDiff($Aggregation.mvyt24be_start_date, @ASOF_DATE)))+$Aggregation.mvyt24be_lcy_amount)/(@dateDiff($Aggregation.mvyt24be_start_date, @ASOF_DATE)+1) END) ELSE (CASE WHEN $saldos_medios_prev.saldo_medio_07 IS NULL THEN $Aggregation.mvyt24be_lcy_amount/(@toNumber(@subStr(@dateToCharODBCFormat(@ASOF_DATE), 9, 2))) ELSE (($saldos_medios_prev.saldo_medio_07*(@toNumber(@subStr(@dateToCharODBCFormat(@ASOF_DATE), 9, 2))-1))+$Aggregation.mvyt24be_lcy_amount)/(@toNumber(@subStr(@dateToCharODBCFormat(@ASOF_DATE), 9, 2))) END) END) END) END) ELSE (CASE WHEN $saldos_medios_prev.saldo_medio_07 IS NULL THEN 0 ELSE $saldos_medios_prev.saldo_medio_07 END) END",
                                    "_name":"expression"
                                 },
                                 {
                                    "string":"FLOAT",
                                    "_name":"valueType"
                                 },
                                 {
                                    "false":"",
                                    "_name":"valueNullable"
                                 }
                              ],
                              "_id":"3aaa3bdd-6dc6-4309-a1da-d1bb9b0f2ada:ModifyModel[1efebe4a-1dcb-4dcb-9623-079468ae41d2].Aggregation[8d725237-1404-45ca-b175-4e3043d19068]"
                           },
                           "_name":"fieldMapping"
                        },
                        "_id":"a411af45-ec4b-43a1-a505-70e80052292c"
                     },
                     "_name":"saldo_medio_07",
                     "_type":"fieldMappingNode"
                  },
                  {
                     "parameters":{
                        "param":{
                           "paramLine":{
                              "param":[
                                 {
                                    "string":"Motor_saldos:ModifyModel[carga_saldos].Aggregation[BBEE_PRE]",
                                    "_name":"model"
                                 },
                                 {
                                    "string":"CASE WHEN @subStr(@dateToCharODBCFormat(@ASOF_DATE), 6, 2) = '08' THEN (CASE WHEN @ASOF_DATE = $Aggregation.mvyt24be_start_date THEN $Aggregation.mvyt24be_lcy_amount ELSE (CASE WHEN subStr(@dateToCharODBCFormat(@ASOF_DATE), 9,2) = '08' THEN $Aggregation.mvyt24be_lcy_amount ELSE (CASE WHEN @subStr(@dateToCharODBCFormat(@ASOF_DATE), 1, 7) = @subStr(@dateToCharODBCFormat($Aggregation.mvyt24be_start_date), 1, 7) THEN (CASE WHEN $saldos_medios_prev.saldo_medio_08 IS NULL THEN $Aggregation.mvyt24be_lcy_amount/(@dateDiff($Aggregation.mvyt24be_start_date, @ASOF_DATE)+1) ELSE (($saldos_medios_prev.saldo_medio_08*(@dateDiff($Aggregation.mvyt24be_start_date, @ASOF_DATE)))+$Aggregation.mvyt24be_lcy_amount)/(@dateDiff($Aggregation.mvyt24be_start_date, @ASOF_DATE)+1) END) ELSE (CASE WHEN $saldos_medios_prev.saldo_medio_08 IS NULL THEN $Aggregation.mvyt24be_lcy_amount/(@toNumber(@subStr(@dateToCharODBCFormat(@ASOF_DATE), 9, 2))) ELSE (($saldos_medios_prev.saldo_medio_08*(@toNumber(@subStr(@dateToCharODBCFormat(@ASOF_DATE), 9, 2))-1))+$Aggregation.mvyt24be_lcy_amount)/(@toNumber(@subStr(@dateToCharODBCFormat(@ASOF_DATE), 9, 2))) END) END) END) END) ELSE (CASE WHEN $saldos_medios_prev.saldo_medio_08 IS NULL THEN 0 ELSE $saldos_medios_prev.saldo_medio_08 END) END",
                                    "_name":"expression"
                                 },
                                 {
                                    "string":"FLOAT",
                                    "_name":"valueType"
                                 },
                                 {
                                    "false":"",
                                    "_name":"valueNullable"
                                 }
                              ],
                              "_id":"3aaa3bdd-6dc6-4309-a1da-d1bb9b0f2ada:ModifyModel[1efebe4a-1dcb-4dcb-9623-079468ae41d2].Aggregation[8d725237-1404-45ca-b175-4e3043d19068]"
                           },
                           "_name":"fieldMapping"
                        },
                        "_id":"fe448f94-0020-46d6-806a-d7236b3b1960"
                     },
                     "_name":"saldo_medio_08",
                     "_type":"fieldMappingNode"
                  },
                  {
                     "parameters":{
                        "param":{
                           "paramLine":{
                              "param":[
                                 {
                                    "string":"Motor_saldos:ModifyModel[carga_saldos].Aggregation[BBEE_PRE]",
                                    "_name":"model"
                                 },
                                 {
                                    "string":"CASE WHEN @subStr(@dateToCharODBCFormat(@ASOF_DATE), 6, 2) = '09' THEN (CASE WHEN @ASOF_DATE = $Aggregation.mvyt24be_start_date THEN $Aggregation.mvyt24be_lcy_amount ELSE (CASE WHEN subStr(@dateToCharODBCFormat(@ASOF_DATE), 9,2) = '09' THEN $Aggregation.mvyt24be_lcy_amount ELSE (CASE WHEN @subStr(@dateToCharODBCFormat(@ASOF_DATE), 1, 7) = @subStr(@dateToCharODBCFormat($Aggregation.mvyt24be_start_date), 1, 7) THEN (CASE WHEN $saldos_medios_prev.saldo_medio_09 IS NULL THEN $Aggregation.mvyt24be_lcy_amount/(@dateDiff($Aggregation.mvyt24be_start_date, @ASOF_DATE)+1) ELSE (($saldos_medios_prev.saldo_medio_09*(@dateDiff($Aggregation.mvyt24be_start_date, @ASOF_DATE)))+$Aggregation.mvyt24be_lcy_amount)/(@dateDiff($Aggregation.mvyt24be_start_date, @ASOF_DATE)+1) END) ELSE (CASE WHEN $saldos_medios_prev.saldo_medio_09 IS NULL THEN $Aggregation.mvyt24be_lcy_amount/(@toNumber(@subStr(@dateToCharODBCFormat(@ASOF_DATE), 9, 2))) ELSE (($saldos_medios_prev.saldo_medio_09*(@toNumber(@subStr(@dateToCharODBCFormat(@ASOF_DATE), 9, 2))-1))+$Aggregation.mvyt24be_lcy_amount)/(@toNumber(@subStr(@dateToCharODBCFormat(@ASOF_DATE), 9, 2))) END) END) END) END) ELSE (CASE WHEN $saldos_medios_prev.saldo_medio_09 IS NULL THEN 0 ELSE $saldos_medios_prev.saldo_medio_09 END) END",
                                    "_name":"expression"
                                 },
                                 {
                                    "string":"FLOAT",
                                    "_name":"valueType"
                                 },
                                 {
                                    "false":"",
                                    "_name":"valueNullable"
                                 }
                              ],
                              "_id":"3aaa3bdd-6dc6-4309-a1da-d1bb9b0f2ada:ModifyModel[1efebe4a-1dcb-4dcb-9623-079468ae41d2].Aggregation[8d725237-1404-45ca-b175-4e3043d19068]"
                           },
                           "_name":"fieldMapping"
                        },
                        "_id":"e8c5043a-8346-4396-b364-e552905857d6"
                     },
                     "_name":"saldo_medio_09",
                     "_type":"fieldMappingNode"
                  },
                  {
                     "parameters":{
                        "param":{
                           "paramLine":{
                              "param":[
                                 {
                                    "string":"Motor_saldos:ModifyModel[carga_saldos].Aggregation[BBEE_PRE]",
                                    "_name":"model"
                                 },
                                 {
                                    "string":"CASE WHEN @subStr(@dateToCharODBCFormat(@ASOF_DATE), 6, 2) = '10' THEN (CASE WHEN @ASOF_DATE = $Aggregation.mvyt24be_start_date THEN $Aggregation.mvyt24be_lcy_amount ELSE (CASE WHEN subStr(@dateToCharODBCFormat(@ASOF_DATE), 9,2) = '10' THEN $Aggregation.mvyt24be_lcy_amount ELSE (CASE WHEN @subStr(@dateToCharODBCFormat(@ASOF_DATE), 1, 7) = @subStr(@dateToCharODBCFormat($Aggregation.mvyt24be_start_date), 1, 7) THEN (CASE WHEN $saldos_medios_prev.saldo_medio_10 IS NULL THEN $Aggregation.mvyt24be_lcy_amount/(@dateDiff($Aggregation.mvyt24be_start_date, @ASOF_DATE)+1) ELSE (($saldos_medios_prev.saldo_medio_10*(@dateDiff($Aggregation.mvyt24be_start_date, @ASOF_DATE)))+$Aggregation.mvyt24be_lcy_amount)/(@dateDiff($Aggregation.mvyt24be_start_date, @ASOF_DATE)+1) END) ELSE (CASE WHEN $saldos_medios_prev.saldo_medio_10 IS NULL THEN $Aggregation.mvyt24be_lcy_amount/(@toNumber(@subStr(@dateToCharODBCFormat(@ASOF_DATE), 9, 2))) ELSE (($saldos_medios_prev.saldo_medio_10*(@toNumber(@subStr(@dateToCharODBCFormat(@ASOF_DATE), 9, 2))-1))+$Aggregation.mvyt24be_lcy_amount)/(@toNumber(@subStr(@dateToCharODBCFormat(@ASOF_DATE), 9, 2))) END) END) END) END) ELSE (CASE WHEN $saldos_medios_prev.saldo_medio_10 IS NULL THEN 0 ELSE $saldos_medios_prev.saldo_medio_10 END) END",
                                    "_name":"expression"
                                 },
                                 {
                                    "string":"FLOAT",
                                    "_name":"valueType"
                                 },
                                 {
                                    "false":"",
                                    "_name":"valueNullable"
                                 }
                              ],
                              "_id":"3aaa3bdd-6dc6-4309-a1da-d1bb9b0f2ada:ModifyModel[1efebe4a-1dcb-4dcb-9623-079468ae41d2].Aggregation[8d725237-1404-45ca-b175-4e3043d19068]"
                           },
                           "_name":"fieldMapping"
                        },
                        "_id":"d1a9c191-77ab-42d2-a8eb-a2f9e4c89499"
                     },
                     "_name":"saldo_medio_10",
                     "_type":"fieldMappingNode"
                  },
                  {
                     "parameters":{
                        "param":{
                           "paramLine":{
                              "param":[
                                 {
                                    "string":"Motor_saldos:ModifyModel[carga_saldos].Aggregation[BBEE_PRE]",
                                    "_name":"model"
                                 },
                                 {
                                    "string":"CASE WHEN @subStr(@dateToCharODBCFormat(@ASOF_DATE), 6, 2) = '11' THEN (CASE WHEN @ASOF_DATE = $Aggregation.mvyt24be_start_date THEN $Aggregation.mvyt24be_lcy_amount ELSE (CASE WHEN subStr(@dateToCharODBCFormat(@ASOF_DATE), 9,2) = '11' THEN $Aggregation.mvyt24be_lcy_amount ELSE (CASE WHEN @subStr(@dateToCharODBCFormat(@ASOF_DATE), 1, 7) = @subStr(@dateToCharODBCFormat($Aggregation.mvyt24be_start_date), 1, 7) THEN (CASE WHEN $saldos_medios_prev.saldo_medio_11 IS NULL THEN $Aggregation.mvyt24be_lcy_amount/(@dateDiff($Aggregation.mvyt24be_start_date, @ASOF_DATE)+1) ELSE (($saldos_medios_prev.saldo_medio_11*(@dateDiff($Aggregation.mvyt24be_start_date, @ASOF_DATE)))+$Aggregation.mvyt24be_lcy_amount)/(@dateDiff($Aggregation.mvyt24be_start_date, @ASOF_DATE)+1) END) ELSE (CASE WHEN $saldos_medios_prev.saldo_medio_11 IS NULL THEN $Aggregation.mvyt24be_lcy_amount/(@toNumber(@subStr(@dateToCharODBCFormat(@ASOF_DATE), 9, 2))) ELSE (($saldos_medios_prev.saldo_medio_11*(@toNumber(@subStr(@dateToCharODBCFormat(@ASOF_DATE), 9, 2))-1))+$Aggregation.mvyt24be_lcy_amount)/(@toNumber(@subStr(@dateToCharODBCFormat(@ASOF_DATE), 9, 2))) END) END) END) END) ELSE (CASE WHEN $saldos_medios_prev.saldo_medio_11 IS NULL THEN 0 ELSE $saldos_medios_prev.saldo_medio_11 END) END",
                                    "_name":"expression"
                                 },
                                 {
                                    "string":"FLOAT",
                                    "_name":"valueType"
                                 },
                                 {
                                    "false":"",
                                    "_name":"valueNullable"
                                 }
                              ],
                              "_id":"3aaa3bdd-6dc6-4309-a1da-d1bb9b0f2ada:ModifyModel[1efebe4a-1dcb-4dcb-9623-079468ae41d2].Aggregation[8d725237-1404-45ca-b175-4e3043d19068]"
                           },
                           "_name":"fieldMapping"
                        },
                        "_id":"ca5bf519-ce22-4598-9143-d82f427ed6e5"
                     },
                     "_name":"saldo_medio_11",
                     "_type":"fieldMappingNode"
                  },
                  {
                     "parameters":{
                        "param":{
                           "paramLine":{
                              "param":[
                                 {
                                    "string":"Motor_saldos:ModifyModel[carga_saldos].Aggregation[BBEE_PRE]",
                                    "_name":"model"
                                 },
                                 {
                                    "string":"CASE WHEN @subStr(@dateToCharODBCFormat(@ASOF_DATE), 6, 2) = '12' THEN (CASE WHEN @ASOF_DATE = $Aggregation.mvyt24be_start_date THEN $Aggregation.mvyt24be_lcy_amount ELSE (CASE WHEN subStr(@dateToCharODBCFormat(@ASOF_DATE), 9,2) = '12' THEN $Aggregation.mvyt24be_lcy_amount ELSE (CASE WHEN @subStr(@dateToCharODBCFormat(@ASOF_DATE), 1, 7) = @subStr(@dateToCharODBCFormat($Aggregation.mvyt24be_start_date), 1, 7) THEN (CASE WHEN $saldos_medios_prev.saldo_medio_12 IS NULL THEN $Aggregation.mvyt24be_lcy_amount/(@dateDiff($Aggregation.mvyt24be_start_date, @ASOF_DATE)+1) ELSE (($saldos_medios_prev.saldo_medio_12*(@dateDiff($Aggregation.mvyt24be_start_date, @ASOF_DATE)))+$Aggregation.mvyt24be_lcy_amount)/(@dateDiff($Aggregation.mvyt24be_start_date, @ASOF_DATE)+1) END) ELSE (CASE WHEN $saldos_medios_prev.saldo_medio_12 IS NULL THEN $Aggregation.mvyt24be_lcy_amount/(@toNumber(@subStr(@dateToCharODBCFormat(@ASOF_DATE), 9, 2))) ELSE (($saldos_medios_prev.saldo_medio_12*(@toNumber(@subStr(@dateToCharODBCFormat(@ASOF_DATE), 9, 2))-1))+$Aggregation.mvyt24be_lcy_amount)/(@toNumber(@subStr(@dateToCharODBCFormat(@ASOF_DATE), 9, 2))) END) END) END) END) ELSE (CASE WHEN $saldos_medios_prev.saldo_medio_12 IS NULL THEN 0 ELSE $saldos_medios_prev.saldo_medio_12 END) END",
                                    "_name":"expression"
                                 },
                                 {
                                    "string":"FLOAT",
                                    "_name":"valueType"
                                 },
                                 {
                                    "false":"",
                                    "_name":"valueNullable"
                                 }
                              ],
                              "_id":"3aaa3bdd-6dc6-4309-a1da-d1bb9b0f2ada:ModifyModel[1efebe4a-1dcb-4dcb-9623-079468ae41d2].Aggregation[8d725237-1404-45ca-b175-4e3043d19068]"
                           },
                           "_name":"fieldMapping"
                        },
                        "_id":"f84146e9-c8e9-4201-aac1-8c9563483cdc"
                     },
                     "_name":"saldo_medio_12",
                     "_type":"fieldMappingNode"
                  },
                  {
                     "parameters":{
                        "param":{
                           "paramLine":{
                              "param":[
                                 {
                                    "string":"Motor_saldos:ModifyModel[carga_saldos].Aggregation[BBEE_PRE]",
                                    "_name":"model"
                                 },
                                 {
                                    "string":"CASE WHEN @subStr(@dateToCharODBCFormat(@ASOF_DATE), 6, 2) IN ('01','02','03') THEN (CASE WHEN @ASOF_DATE = $Aggregation.mvyt24be_start_date THEN \t$Aggregation.mvyt24be_lcy_amount ELSE (CASE WHEN subStr(@dateToCharODBCFormat(@ASOF_DATE), 6,5) = '01-01' THEN $Aggregation.mvyt24be_lcy_amount \tELSE (CASE WHEN @subStr(@dateToCharODBCFormat(@ASOF_DATE), 1, 4) = @subStr(@dateToCharODBCFormat($Aggregation.mvyt24be_start_date), 1, 4) AND @subStr(@dateToCharODBCFormat($Aggregation.mvyt24be_start_date), 6, 2) IN ('01','02','03') THEN (CASE WHEN $saldos_medios_prev.saldo_medio_1T IS NULL THEN $Aggregation.mvyt24be_lcy_amount/(@dateDiff($Aggregation.mvyt24be_start_date, @ASOF_DATE)+1) ELSE \t(($saldos_medios_prev.saldo_medio_1T*(@dateDiff($Aggregation.mvyt24be_start_date, @ASOF_DATE)))+$Aggregation.mvyt24be_lcy_amount)/(@dateDiff($Aggregation.mvyt24be_start_date, @ASOF_DATE)+1) END) ELSE (CASE WHEN $saldos_medios_prev.saldo_medio_1T IS NULL THEN \t$Aggregation.mvyt24be_lcy_amount/(@dateDiff(@toDateODBCFormat(@CONCAT_STR(@subStr(@dateToCharODBCFormat(@ASOF_DATE), 1, 4), '-01-01')), @ASOF_DATE)+1) \tELSE (($saldos_medios_prev.saldo_medio_1T*(@dateDiff(@toDateODBCFormat(@CONCAT_STR(@subStr(@dateToCharODBCFormat(@ASOF_DATE), 1, 4), '-01-01')), @ASOF_DATE)))+$Aggregation.mvyt24be_lcy_amount)/(@dateDiff(@toDateODBCFormat(@CONCAT_STR(@subStr(@dateToCharODBCFormat(@ASOF_DATE), 1, 4), '-01-01')), @ASOF_DATE)+1) END) END) END) END) ELSE (CASE WHEN $saldos_medios_prev.saldo_medio_1T IS NULL THEN 0 ELSE $saldos_medios_prev.saldo_medio_1T  END) END",
                                    "_name":"expression"
                                 },
                                 {
                                    "string":"FLOAT",
                                    "_name":"valueType"
                                 },
                                 {
                                    "false":"",
                                    "_name":"valueNullable"
                                 }
                              ],
                              "_id":"3aaa3bdd-6dc6-4309-a1da-d1bb9b0f2ada:ModifyModel[1efebe4a-1dcb-4dcb-9623-079468ae41d2].Aggregation[8d725237-1404-45ca-b175-4e3043d19068]"
                           },
                           "_name":"fieldMapping"
                        },
                        "_id":"5b085fca-0221-4c75-9aed-d5ce0172852e"
                     },
                     "_name":"saldo_medio_1T",
                     "_type":"fieldMappingNode"
                  },
                  {
                     "parameters":{
                        "param":{
                           "paramLine":{
                              "param":[
                                 {
                                    "string":"Motor_saldos:ModifyModel[carga_saldos].Aggregation[BBEE_PRE]",
                                    "_name":"model"
                                 },
                                 {
                                    "string":"CASE WHEN @subStr(@dateToCharODBCFormat(@ASOF_DATE), 6, 2) IN ('04','05','06') THEN (CASE WHEN @ASOF_DATE = $Aggregation.mvyt24be_start_date THEN \t$Aggregation.mvyt24be_lcy_amount ELSE (CASE WHEN subStr(@dateToCharODBCFormat(@ASOF_DATE), 6,5) = '01-01' THEN $Aggregation.mvyt24be_lcy_amount \tELSE (CASE WHEN @subStr(@dateToCharODBCFormat(@ASOF_DATE), 1, 4) = @subStr(@dateToCharODBCFormat($Aggregation.mvyt24be_start_date), 1, 4) AND @subStr(@dateToCharODBCFormat($Aggregation.mvyt24be_start_date), 6, 2) IN ('04','05','06') THEN (CASE WHEN $saldos_medios_prev.saldo_medio_2T IS NULL THEN $Aggregation.mvyt24be_lcy_amount/(@dateDiff($Aggregation.mvyt24be_start_date, @ASOF_DATE)+1) ELSE \t(($saldos_medios_prev.saldo_medio_2T*(@dateDiff($Aggregation.mvyt24be_start_date, @ASOF_DATE)))+$Aggregation.mvyt24be_lcy_amount)/(@dateDiff($Aggregation.mvyt24be_start_date, @ASOF_DATE)+1) END) ELSE (CASE WHEN $saldos_medios_prev.saldo_medio_2T IS NULL THEN \t$Aggregation.mvyt24be_lcy_amount/(@dateDiff(@toDateODBCFormat(@CONCAT_STR(@subStr(@dateToCharODBCFormat(@ASOF_DATE), 1, 4), '-04-01')), @ASOF_DATE)+1) \tELSE (($saldos_medios_prev.saldo_medio_2T*(@dateDiff(@toDateODBCFormat(@CONCAT_STR(@subStr(@dateToCharODBCFormat(@ASOF_DATE), 1, 4), '-04-01')), @ASOF_DATE)))+$Aggregation.mvyt24be_lcy_amount)/(@dateDiff(@toDateODBCFormat(@CONCAT_STR(@subStr(@dateToCharODBCFormat(@ASOF_DATE), 1, 4), '-04-01')), @ASOF_DATE)+1) END) END) END) END) ELSE (CASE WHEN $saldos_medios_prev.saldo_medio_2T IS NULL THEN 0 ELSE $saldos_medios_prev.saldo_medio_2T  END) END",
                                    "_name":"expression"
                                 },
                                 {
                                    "string":"FLOAT",
                                    "_name":"valueType"
                                 },
                                 {
                                    "false":"",
                                    "_name":"valueNullable"
                                 }
                              ],
                              "_id":"3aaa3bdd-6dc6-4309-a1da-d1bb9b0f2ada:ModifyModel[1efebe4a-1dcb-4dcb-9623-079468ae41d2].Aggregation[8d725237-1404-45ca-b175-4e3043d19068]"
                           },
                           "_name":"fieldMapping"
                        },
                        "_id":"552ada77-8836-4c3b-b115-a3efbeb03465"
                     },
                     "_name":"saldo_medio_2T",
                     "_type":"fieldMappingNode"
                  },
                  {
                     "parameters":{
                        "param":{
                           "paramLine":{
                              "param":[
                                 {
                                    "string":"Motor_saldos:ModifyModel[carga_saldos].Aggregation[BBEE_PRE]",
                                    "_name":"model"
                                 },
                                 {
                                    "string":"CASE WHEN @subStr(@dateToCharODBCFormat(@ASOF_DATE), 6, 2) IN ('07','08','09') THEN (CASE WHEN @ASOF_DATE = $Aggregation.mvyt24be_start_date THEN \t$Aggregation.mvyt24be_lcy_amount ELSE (CASE WHEN subStr(@dateToCharODBCFormat(@ASOF_DATE), 6,5) = '01-01' THEN $Aggregation.mvyt24be_lcy_amount \tELSE (CASE WHEN @subStr(@dateToCharODBCFormat(@ASOF_DATE), 1, 4) = @subStr(@dateToCharODBCFormat($Aggregation.mvyt24be_start_date), 1, 4) AND @subStr(@dateToCharODBCFormat($Aggregation.mvyt24be_start_date), 6, 2) IN ('07','08','09') THEN (CASE WHEN $saldos_medios_prev.saldo_medio_3T IS NULL THEN $Aggregation.mvyt24be_lcy_amount/(@dateDiff($Aggregation.mvyt24be_start_date, @ASOF_DATE)+1) ELSE \t(($saldos_medios_prev.saldo_medio_3T*(@dateDiff($Aggregation.mvyt24be_start_date, @ASOF_DATE)))+$Aggregation.mvyt24be_lcy_amount)/(@dateDiff($Aggregation.mvyt24be_start_date, @ASOF_DATE)+1) END) ELSE (CASE WHEN $saldos_medios_prev.saldo_medio_3T IS NULL THEN \t$Aggregation.mvyt24be_lcy_amount/(@dateDiff(@toDateODBCFormat(@CONCAT_STR(@subStr(@dateToCharODBCFormat(@ASOF_DATE), 1, 4), '-07-01')), @ASOF_DATE)+1) \tELSE (($saldos_medios_prev.saldo_medio_3T*(@dateDiff(@toDateODBCFormat(@CONCAT_STR(@subStr(@dateToCharODBCFormat(@ASOF_DATE), 1, 4), '-07-01')), @ASOF_DATE)))+$Aggregation.mvyt24be_lcy_amount)/(@dateDiff(@toDateODBCFormat(@CONCAT_STR(@subStr(@dateToCharODBCFormat(@ASOF_DATE), 1, 4), '-07-01')), @ASOF_DATE)+1) END) END) END) END) ELSE (CASE WHEN $saldos_medios_prev.saldo_medio_3T IS NULL THEN 0 ELSE $saldos_medios_prev.saldo_medio_3T  END) END",
                                    "_name":"expression"
                                 },
                                 {
                                    "string":"FLOAT",
                                    "_name":"valueType"
                                 },
                                 {
                                    "false":"",
                                    "_name":"valueNullable"
                                 }
                              ],
                              "_id":"3aaa3bdd-6dc6-4309-a1da-d1bb9b0f2ada:ModifyModel[1efebe4a-1dcb-4dcb-9623-079468ae41d2].Aggregation[8d725237-1404-45ca-b175-4e3043d19068]"
                           },
                           "_name":"fieldMapping"
                        },
                        "_id":"4e940519-40c5-4db5-b83b-61760a04f71c"
                     },
                     "_name":"saldo_medio_3T",
                     "_type":"fieldMappingNode"
                  },
                  {
                     "parameters":{
                        "param":{
                           "paramLine":{
                              "param":[
                                 {
                                    "string":"Motor_saldos:ModifyModel[carga_saldos].Aggregation[BBEE_PRE]",
                                    "_name":"model"
                                 },
                                 {
                                    "string":"CASE WHEN @subStr(@dateToCharODBCFormat(@ASOF_DATE), 6, 2) IN ('10','11','12') THEN (CASE WHEN @ASOF_DATE = $Aggregation.mvyt24be_start_date THEN \t$Aggregation.mvyt24be_lcy_amount ELSE (CASE WHEN subStr(@dateToCharODBCFormat(@ASOF_DATE), 6,5) = '01-01' THEN $Aggregation.mvyt24be_lcy_amount \tELSE (CASE WHEN @subStr(@dateToCharODBCFormat(@ASOF_DATE), 1, 4) = @subStr(@dateToCharODBCFormat($Aggregation.mvyt24be_start_date), 1, 4) AND @subStr(@dateToCharODBCFormat($Aggregation.mvyt24be_start_date), 6, 2) IN ('10','11','12') THEN (CASE WHEN $saldos_medios_prev.saldo_medio_4T IS NULL THEN $Aggregation.mvyt24be_lcy_amount/(@dateDiff($Aggregation.mvyt24be_start_date, @ASOF_DATE)+1) ELSE \t(($saldos_medios_prev.saldo_medio_4T*(@dateDiff($Aggregation.mvyt24be_start_date, @ASOF_DATE)))+$Aggregation.mvyt24be_lcy_amount)/(@dateDiff($Aggregation.mvyt24be_start_date, @ASOF_DATE)+1) END) ELSE (CASE WHEN $saldos_medios_prev.saldo_medio_4T IS NULL THEN \t$Aggregation.mvyt24be_lcy_amount/(@dateDiff(@toDateODBCFormat(@CONCAT_STR(@subStr(@dateToCharODBCFormat(@ASOF_DATE), 1, 4), '-10-01')), @ASOF_DATE)+1) \tELSE (($saldos_medios_prev.saldo_medio_4T*(@dateDiff(@toDateODBCFormat(@CONCAT_STR(@subStr(@dateToCharODBCFormat(@ASOF_DATE), 1, 4), '-10-01')), @ASOF_DATE)))+$Aggregation.mvyt24be_lcy_amount)/(@dateDiff(@toDateODBCFormat(@CONCAT_STR(@subStr(@dateToCharODBCFormat(@ASOF_DATE), 1, 4), '-10-01')), @ASOF_DATE)+1) END) END) END) END) ELSE (CASE WHEN $saldos_medios_prev.saldo_medio_4T IS NULL THEN 0 ELSE $saldos_medios_prev.saldo_medio_4T  END) END",
                                    "_name":"expression"
                                 },
                                 {
                                    "string":"FLOAT",
                                    "_name":"valueType"
                                 },
                                 {
                                    "false":"",
                                    "_name":"valueNullable"
                                 }
                              ],
                              "_id":"3aaa3bdd-6dc6-4309-a1da-d1bb9b0f2ada:ModifyModel[1efebe4a-1dcb-4dcb-9623-079468ae41d2].Aggregation[8d725237-1404-45ca-b175-4e3043d19068]"
                           },
                           "_name":"fieldMapping"
                        },
                        "_id":"4e46216a-c99b-4ef8-b48d-7cc13c2d3ed3"
                     },
                     "_name":"saldo_medio_4T",
                     "_type":"fieldMappingNode"
                  },
                  {
                     "parameters":{
                        "param":{
                           "paramLine":{
                              "param":[
                                 {
                                    "string":"Motor_saldos:ModifyModel[carga_saldos].Aggregation[BBEE_PRE]",
                                    "_name":"model"
                                 },
                                 {
                                    "string":"CASE WHEN @ASOF_DATE = $Aggregation.mvyt24be_start_date THEN $Aggregation.mvyt24be_lcy_amount ELSE (CASE WHEN subStr(@dateToCharODBCFormat(@ASOF_DATE), 6,5) = '01-01' THEN $Aggregation.mvyt24be_lcy_amount ELSE (CASE WHEN @subStr(@dateToCharODBCFormat(@ASOF_DATE), 1, 4) = @subStr(@dateToCharODBCFormat($Aggregation.mvyt24be_start_date), 1, 4) THEN (CASE WHEN $saldos_medios_prev.saldo_medio_anual IS NULL THEN $Aggregation.mvyt24be_lcy_amount/(@dateDiff($Aggregation.mvyt24be_start_date, @ASOF_DATE)+1) ELSE  (($saldos_medios_prev.saldo_medio_anual*(@dateDiff($Aggregation.mvyt24be_start_date, @ASOF_DATE)))+$Aggregation.mvyt24be_lcy_amount)/(@dateDiff($Aggregation.mvyt24be_start_date, @ASOF_DATE)+1) END) ELSE (CASE WHEN $saldos_medios_prev.saldo_medio_anual IS NULL THEN  $Aggregation.mvyt24be_lcy_amount/(@dateDiff(@toDateODBCFormat(@CONCAT_STR(@subStr(@dateToCharODBCFormat(@ASOF_DATE), 1, 4), '-01-01')), @ASOF_DATE)+1) ELSE (($saldos_medios_prev.saldo_medio_anual*(@dateDiff(@toDateODBCFormat(@CONCAT_STR(@subStr(@dateToCharODBCFormat(@ASOF_DATE), 1, 4), '-01-01')), @ASOF_DATE)))+$Aggregation.mvyt24be_lcy_amount)/(@dateDiff(@toDateODBCFormat(@CONCAT_STR(@subStr(@dateToCharODBCFormat(@ASOF_DATE), 1, 4), '-01-01')), @ASOF_DATE)+1) END) END) END) END",
                                    "_name":"expression"
                                 },
                                 {
                                    "string":"FLOAT",
                                    "_name":"valueType"
                                 },
                                 {
                                    "false":"",
                                    "_name":"valueNullable"
                                 }
                              ],
                              "_id":"3aaa3bdd-6dc6-4309-a1da-d1bb9b0f2ada:ModifyModel[1efebe4a-1dcb-4dcb-9623-079468ae41d2].Aggregation[8d725237-1404-45ca-b175-4e3043d19068]"
                           },
                           "_name":"fieldMapping"
                        },
                        "_id":"a0eb8b59-741d-489a-8f56-68e10443c44c"
                     },
                     "_name":"saldo_medio_anual",
                     "_type":"fieldMappingNode"
                  },
                  {
                     "parameters":{
                        "param":{
                           "paramLine":{
                              "param":[
                                 {
                                    "string":"Motor_saldos:ModifyModel[carga_saldos].Aggregation[BBEE_PRE]",
                                    "_name":"model"
                                 },
                                 {
                                    "string":"CASE WHEN subStr(@dateToCharODBCFormat(@ASOF_DATE), 6,5) = '31-12' OR @dateDiff(@ASOF_DATE, @toDateODBCFormat(@CONCAT_STR(@CONCAT_STR(@CONCAT_STR(@subStr(@dateToCharODBCFormat(@ASOF_DATE), 1, 4), '-'), @numberToChar(@toNumber(subStr(@dateToCharODBCFormat(@ASOF_DATE), 6,2))+1)), '-01'))) = 1 THEN (CASE WHEN subStr(@dateToCharODBCFormat(@ASOF_DATE), 6,2) = '01' THEN $Aggregation.mvyt24be_lcy_amount ELSE (CASE WHEN @subStr(@dateToCharODBCFormat(@ASOF_DATE), 1, 7) = @subStr(@dateToCharODBCFormat($Aggregation.mvyt24be_start_date), 1, 7) THEN $Aggregation.mvyt24be_lcy_amount ELSE (CASE WHEN @subStr(@dateToCharODBCFormat(@ASOF_DATE), 1, 4) = @subStr(@dateToCharODBCFormat($Aggregation.mvyt24be_start_date), 1, 4) THEN (CASE WHEN $saldos_medios_prev.saldo_mensual_medio_anual IS NULL THEN $Aggregation.mvyt24be_lcy_amount/(@toNumber(@subStr(@dateToCharODBCFormat(@ASOF_DATE), 6, 2))- @toNumber(@subStr(@dateToCharODBCFormat($Aggregation.mvyt24be_start_date), 6, 2))) ELSE  (($saldos_medios_prev.saldo_mensual_medio_anual*(@toNumber(@subStr(@dateToCharODBCFormat(@ASOF_DATE), 6, 2))- @toNumber(@subStr(@dateToCharODBCFormat($Aggregation.mvyt24be_start_date), 6, 2)))) + $Aggregation.mvyt24be_lcy_amount)/(@toNumber(@subStr(@dateToCharODBCFormat(@ASOF_DATE), 6, 2)) - @toNumber(@subStr(@dateToCharODBCFormat($Aggregation.mvyt24be_start_date), 6, 2))+1) END) ELSE (CASE WHEN  $saldos_medios_prev.saldo_mensual_medio_anual IS NULL THEN $Aggregation.mvyt24be_lcy_amount/(@toNumber(@subStr(@dateToCharODBCFormat(@ASOF_DATE), 6, 2))) ELSE (($saldos_medios_prev.saldo_mensual_medio_anual*(@toNumber(@subStr(@dateToCharODBCFormat(@ASOF_DATE), 6, 2))-1)) + $Aggregation.mvyt24be_lcy_amount)/(@toNumber(@subStr(@dateToCharODBCFormat(@ASOF_DATE), 6, 2))) END) END) END) END) ELSE (CASE WHEN $saldos_medios_prev.saldo_mensual_medio_anual IS NULL OR @subStr(@dateToCharODBCFormat(@ASOF_DATE), 6, 2) ='01' THEN 0 ELSE $saldos_medios_prev.saldo_mensual_medio_anual END) END",
                                    "_name":"expression"
                                 },
                                 {
                                    "string":"FLOAT",
                                    "_name":"valueType"
                                 },
                                 {
                                    "false":"",
                                    "_name":"valueNullable"
                                 }
                              ],
                              "_id":"3aaa3bdd-6dc6-4309-a1da-d1bb9b0f2ada:ModifyModel[1efebe4a-1dcb-4dcb-9623-079468ae41d2].Aggregation[8d725237-1404-45ca-b175-4e3043d19068]"
                           },
                           "_name":"fieldMapping"
                        },
                        "_id":"057b2c1b-de0f-4a2f-8c00-1a700553122e"
                     },
                     "_name":"saldo_mensual_medio_anual",
                     "_type":"fieldMappingNode"
                  },
                  {
                     "parameters":{
                        "param":{
                           "paramLine":{
                              "param":[
                                 {
                                    "string":"Motor_saldos:ModifyModel[carga_saldos].Aggregation[BBEE_PRE]",
                                    "_name":"model"
                                 },
                                 {
                                    "string":"CASE WHEN subStr(@dateToCharODBCFormat(@ASOF_DATE), 6,5) = '01-01' THEN (CASE WHEN $saldos_medios_prev.saldo_medio_anual IS NULL THEN 0 ELSE $saldos_medios_prev.saldo_medio_anual END) ELSE (CASE WHEN $saldos_medios_prev.saldo_medio_anual_anterior IS NULL THEN 0 ELSE $saldos_medios_prev.saldo_medio_anual_anterior END) END",
                                    "_name":"expression"
                                 },
                                 {
                                    "string":"FLOAT",
                                    "_name":"valueType"
                                 },
                                 {
                                    "false":"",
                                    "_name":"valueNullable"
                                 }
                              ],
                              "_id":"3aaa3bdd-6dc6-4309-a1da-d1bb9b0f2ada:ModifyModel[1efebe4a-1dcb-4dcb-9623-079468ae41d2].Aggregation[8d725237-1404-45ca-b175-4e3043d19068]"
                           },
                           "_name":"fieldMapping"
                        },
                        "_id":"01d68a01-cc2c-451a-b163-91b062bbfcea"
                     },
                     "_name":"saldo_medio_anual_anterior",
                     "_type":"fieldMappingNode"
                  },
                  {
                     "parameters":{
                        "param":{
                           "paramLine":{
                              "param":[
                                 {
                                    "string":"Motor_saldos:ModifyModel[carga_saldos].Aggregation[BBEE_PRE]",
                                    "_name":"model"
                                 },
                                 {
                                    "string":"CASE WHEN subStr(@dateToCharODBCFormat(@ASOF_DATE), 6,5) = '01-01' THEN (CASE WHEN $saldos_medios_prev.saldo_mensual_medio_anual IS NULL THEN 0 ELSE $saldos_medios_prev.saldo_mensual_medio_anual END) ELSE (CASE WHEN $saldos_medios_prev.saldo_mensual_medio_anual_anterior IS NULL THEN 0 ELSE $saldos_medios_prev.saldo_mensual_medio_anual_anterior END) END",
                                    "_name":"expression"
                                 },
                                 {
                                    "string":"FLOAT",
                                    "_name":"valueType"
                                 },
                                 {
                                    "false":"",
                                    "_name":"valueNullable"
                                 }
                              ],
                              "_id":"3aaa3bdd-6dc6-4309-a1da-d1bb9b0f2ada:ModifyModel[1efebe4a-1dcb-4dcb-9623-079468ae41d2].Aggregation[8d725237-1404-45ca-b175-4e3043d19068]"
                           },
                           "_name":"fieldMapping"
                        },
                        "_id":"24729d57-f2f9-4e49-8139-a31f4d0c4e1d"
                     },
                     "_name":"saldo_mensual_medio_anual_anterior",
                     "_type":"fieldMappingNode"
                  }
               ],
               "_name":"Calculated Fields Mapping",
               "_type":"calcGroup"
            }
         ],
         "_name":"Mapping",
         "_type":"rootMappingNode"
      }
   }
}